video_fragment_ingest/__init__.py
video_fragment_ingest/_gst_mpegts_decoder_pipeline.py
video_fragment_ingest/video_ingest_fragment_consumer.py
video_fragment_ingest/video_ingest_fragment_decoded_frame.py
video_fragment_ingest/video_ingest_fragment_metric.py
video_fragment_ingest/video_ingest_fragment_pipeline.py
video_fragment_ingest/_generated/__init__.py
video_fragment_ingest/_generated/api/analytics_service_pb2.py
video_fragment_ingest/_generated/api/analytics_service_pb2.pyi
video_fragment_ingest/_generated/api/analytics_service_pb2_grpc.py
video_fragment_ingest/_generated/api/camera_model_service_pb2.py
video_fragment_ingest/_generated/api/camera_model_service_pb2.pyi
video_fragment_ingest/_generated/api/camera_model_service_pb2_grpc.py
video_fragment_ingest/_generated/api/cloud_service_pb2.py
video_fragment_ingest/_generated/api/cloud_service_pb2.pyi
video_fragment_ingest/_generated/api/cloud_service_pb2_grpc.py
video_fragment_ingest/_generated/api/core_service_pb2.py
video_fragment_ingest/_generated/api/core_service_pb2.pyi
video_fragment_ingest/_generated/api/core_service_pb2_grpc.py
video_fragment_ingest/_generated/api/data_generation_service_pb2.py
video_fragment_ingest/_generated/api/data_generation_service_pb2.pyi
video_fragment_ingest/_generated/api/data_generation_service_pb2_grpc.py
video_fragment_ingest/_generated/api/debugging_service_pb2.py
video_fragment_ingest/_generated/api/debugging_service_pb2.pyi
video_fragment_ingest/_generated/api/debugging_service_pb2_grpc.py
video_fragment_ingest/_generated/api/device_service_pb2.py
video_fragment_ingest/_generated/api/device_service_pb2.pyi
video_fragment_ingest/_generated/api/device_service_pb2_grpc.py
video_fragment_ingest/_generated/api/feature_store_service_pb2.py
video_fragment_ingest/_generated/api/feature_store_service_pb2.pyi
video_fragment_ingest/_generated/api/feature_store_service_pb2_grpc.py
video_fragment_ingest/_generated/api/heartbeat_service_pb2.py
video_fragment_ingest-0.0.0a16.dist-info/METADATA
video_fragment_ingest-0.0.0a16.dist-info/WHEEL
video_fragment_ingest-0.0.0a16.dist-info/top_level.txt
video_fragment_ingest-0.0.0a16.dist-info/RECORD
