Metadata-Version: 2.1
Name: video-fragment-ingest
Version: 0.0.0a16
Summary: Kafka-based ingest and decoding classes for VideoIngestFragments
Author: Andres Godoy
Author-email: andres@volt.ai
Classifier: Programming Language :: Python :: 3.8
Classifier: License :: OSI Approved :: MIT License
Classifier: Operating System :: OS Independent
Requires-Python: >=3.10
Requires-Dist: boto3>=1.37.0
Requires-Dist: kafka-python>=2.0.4
Requires-Dist: numpy>=1.24.4
